{"chunk_definitions":[{"row":9,"row_count":1,"visible":true,"expansion_state":0,"options":{"engine":"r","label":"setup","include":false},"document_id":"6E1259D6","chunk_id":"csetup_chunk","chunk_label":"setup"},{"row":21,"row_count":1,"visible":true,"expansion_state":0,"options":{"engine":"r","label":"unnamed-chunk-10"},"document_id":"6E1259D6","chunk_id":"cyii6sq2s20k7","chunk_label":"unnamed-chunk-2"},{"row":41,"row_count":1,"visible":true,"expansion_state":0,"options":{"engine":"r","label":"unnamed-chunk-77"},"document_id":"6E1259D6","chunk_id":"c1bmfc51bjo7p","chunk_label":"unnamed-chunk-3"},{"row":68,"row_count":1,"visible":true,"expansion_state":0,"options":{"engine":"r","label":"unnamed-chunk-11"},"document_id":"6E1259D6","chunk_id":"cbdbc8lcy6ast","chunk_label":"unnamed-chunk-5"},{"row":90,"row_count":1,"visible":true,"expansion_state":0,"options":{"engine":"r","label":"unnamed-chunk-13"},"document_id":"6E1259D6","chunk_id":"cp3u46ufafgv4","chunk_label":"unnamed-chunk-6"},{"row":111,"row_count":1,"visible":true,"expansion_state":0,"options":{"engine":"r","label":"unnamed-chunk-40"},"document_id":"6E1259D6","chunk_id":"cbvgkydnqzgfz","chunk_label":"unnamed-chunk-8"}],"doc_write_time":1695411552,"working_dir":null,"default_chunk_options":{"echo":false}}